MANIFEST.in
README.md
setup.cfg
setup.py
docassemble/__init__.py
docassemble.assemblylinewizard.egg-info/PKG-INFO
docassemble.assemblylinewizard.egg-info/SOURCES.txt
docassemble.assemblylinewizard.egg-info/dependency_links.txt
docassemble.assemblylinewizard.egg-info/namespace_packages.txt
docassemble.assemblylinewizard.egg-info/not-zip-safe
docassemble.assemblylinewizard.egg-info/top_level.txt
docassemble/assemblylinewizard/__init__.py
docassemble/assemblylinewizard/assembly_line.py
docassemble/assemblylinewizard/custom_values.py
docassemble/assemblylinewizard/generator_constants.py
docassemble/assemblylinewizard/interview_generator.py
docassemble/assemblylinewizard/test_fill_in_field_attributes.py
docassemble/assemblylinewizard/test_map_names.py
docassemble/assemblylinewizard/data/questions/assembly_line.yml
docassemble/assemblylinewizard/data/questions/feedback.yml
docassemble/assemblylinewizard/data/questions/generator-test.yml
docassemble/assemblylinewizard/data/questions/pdf_field_tester.yml
docassemble/assemblylinewizard/data/questions/signature_tester.yml
docassemble/assemblylinewizard/data/sources/README.md
docassemble/assemblylinewizard/data/sources/output_patterns.yml
docassemble/assemblylinewizard/data/static/README.md
docassemble/assemblylinewizard/data/static/placeholder_signature.png
docassemble/assemblylinewizard/data/static/progressivedisclosure.css
docassemble/assemblylinewizard/data/templates/README.md
docassemble/assemblylinewizard/data/templates/test.pdf
docassemble/assemblylinewizard/data/templates/test_docx.docx
docassemble/assemblylinewizard/data/templates/test_pdf.pdf