Metadata-Version: 2.1
Name: docassemble.assemblylinewizard
Version: 0.81
Summary: UNKNOWN
Home-page: https://docassemble.org
Author: Quinten Steenhuis
Author-email: qsteenhuis@suffolk.edu
License: MIT
Platform: UNKNOWN
